TransCipherTools/__init__.py
TransCipherTools/columnar.py
TransCipherTools/railfence.py
TransCipherTools-0.1.dist-info/License.txt
TransCipherTools-0.1.dist-info/METADATA
TransCipherTools-0.1.dist-info/WHEEL
TransCipherTools-0.1.dist-info/top_level.txt
TransCipherTools-0.1.dist-info/RECORD
