Metadata-Version: 2.1
Name: TransCipherTools
Version: 0.1
Summary: A Python library for the Transposition Cipher techniques  
Home-page: https://github.com/Fluffy-debuger/Transposition_Cipher
Author: Fluffy_Debuger
Author-email: a69247199@gmail.com
Classifier: Programming Language :: Python :: 3
Classifier: License :: OSI Approved :: MIT License
Classifier: Operating System :: OS Independent
Requires-Python: >=3.6
License-File: License.txt
